{
  "auth": {
    "user_pool_id": "eu-west-2_oigA8CyD9",
    "aws_region": "eu-west-2",
    "user_pool_client_id": "6l7bk6qku6belr5outd2ag7jbu",
    "identity_pool_id": "eu-west-2:efa6f2b1-8b21-431a-924a-a6a7e772f4f9",
    "mfa_methods": [],
    "standard_required_attributes": [
      "email"
    ],
    "username_attributes": [
      "email"
    ],
    "user_verification_types": [
      "email"
    ],
    "mfa_configuration": "NONE",
    "password_policy": {
      "min_length": 8,
      "require_lowercase": true,
      "require_numbers": true,
      "require_symbols": true,
      "require_uppercase": true
    },
    "unauthenticated_identities_enabled": true
  },
  "data": {
    "url": "https://o5qk5co4uvezxoxnaqbblg3pxu.appsync-api.eu-west-2.amazonaws.com/graphql",
    "aws_region": "eu-west-2",
    "default_authorization_type": "AWS_IAM",
    "authorization_types": [
      "AMAZON_COGNITO_USER_POOLS"
    ],
    "model_introspection": {
      "version": 1,
      "models": {
        "SessionStorage": {
          "name": "SessionStorage",
          "fields": {
            "id": {
              "name": "id",
              "isArray": false,
              "type": "String",
              "isRequired": true,
              "attributes": []
            },
            "templateType": {
              "name": "templateType",
              "isArray": false,
              "type": {
                "enum": "SessionStorageTemplateType"
              },
              "isRequired": false,
              "attributes": []
            },
            "nhsAppTemplateName": {
              "name": "nhsAppTemplateName",
              "isArray": false,
              "type": "String",
              "isRequired": true,
              "attributes": []
            },
            "nhsAppTemplateMessage": {
              "name": "nhsAppTemplateMessage",
              "isArray": false,
              "type": "String",
              "isRequired": true,
              "attributes": []
            },
            "createdAt": {
              "name": "createdAt",
              "isArray": false,
              "type": "AWSDateTime",
              "isRequired": false,
              "attributes": [],
              "isReadOnly": true
            },
            "updatedAt": {
              "name": "updatedAt",
              "isArray": false,
              "type": "AWSDateTime",
              "isRequired": false,
              "attributes": [],
              "isReadOnly": true
            }
          },
          "syncable": true,
          "pluralName": "SessionStorages",
          "attributes": [
            {
              "type": "model",
              "properties": {}
            },
            {
              "type": "key",
              "properties": {
                "fields": [
                  "id"
                ]
              }
            },
            {
              "type": "auth",
              "properties": {
                "rules": [
                  {
                    "allow": "public",
                    "provider": "iam",
                    "operations": [
                      "create",
                      "update",
                      "delete",
                      "read"
                    ]
                  }
                ]
              }
            }
          ],
          "primaryKeyInfo": {
            "isCustomPrimaryKey": false,
            "primaryKeyFieldName": "id",
            "sortKeyFieldNames": []
          }
        }
      },
      "enums": {
        "SessionStorageTemplateType": {
          "name": "SessionStorageTemplateType",
          "values": [
            "NHS_APP",
            "SMS",
            "EMAIL",
            "LETTER",
            "UNKNOWN"
          ]
        }
      },
      "nonModels": {}
    }
  },
  "version": "1"
}